MANIFEST.in
README.md
setup.py
pypeep/__init__.py
pypeep/client.py
pypeep/common.py
pypeep/logger.py
pypeep/main.py
pypeep.egg-info/PKG-INFO
pypeep.egg-info/SOURCES.txt
pypeep.egg-info/dependency_links.txt
pypeep.egg-info/entry_points.txt
pypeep.egg-info/requires.txt
pypeep.egg-info/top_level.txt