Metadata-Version: 1.1
Name: pypeep
Version: 0.1.1
Summary: debug configurator
Home-page: https://github.com/cuyu/pypeep
Author: cuyu
Author-email: cuyu@splunk.com
License: MIT
Keywords: PyCharm,debug,remote debug
Platform: any
Classifier: Programming Language :: Python :: 2.7
